LICENSE
algoworld_contracts_legacy/__init__.py
algoworld_contracts_legacy/auction/__init__.py
algoworld_contracts_legacy/auction/clear.py
algoworld_contracts_legacy/auction/escrow.py
algoworld_contracts_legacy/auction/helpers/__init__.py
algoworld_contracts_legacy/auction/helpers/state.py
algoworld_contracts_legacy/auction/manager.py
algoworld_contracts_legacy/auction/proxy.py
algoworld_contracts_legacy/common/__init__.py
algoworld_contracts_legacy/common/utils.py
algoworld_contracts_legacy/contracts.py
algoworld_contracts_legacy/swapper/__init__.py
algoworld_contracts_legacy/swapper/asa_to_asa_swapper.py
algoworld_contracts_legacy/swapper/asas_to_algo_swapper.py
algoworld_contracts_legacy/swapper/swap_proxy.py
algoworld_contracts_legacy-1.3.0.dist-info/LICENSE
algoworld_contracts_legacy-1.3.0.dist-info/METADATA
algoworld_contracts_legacy-1.3.0.dist-info/WHEEL
algoworld_contracts_legacy-1.3.0.dist-info/RECORD
