Metadata-Version: 2.1
Name: algoworld-contracts-legacy
Version: 1.3.0
Summary: AlgoWorld Smart Contracts and Signatures
Home-page: https://github.com/AlgoWorldNFT/algoworld-contracts
License: MIT
Keywords: algoworld,algorand,blockchain,pyteal,smart contracts
Author: AlgoWorld
Author-email: info@algoworld.io
Requires-Python: >=3.9,<4.0
Classifier: License :: OSI Approved :: MIT License
Classifier: Programming Language :: Python :: 3
Classifier: Programming Language :: Python :: 3.9
Classifier: Programming Language :: Python :: 3.10
Classifier: Programming Language :: Python :: 3.11
Requires-Dist: PyYAML (==6.0)
Requires-Dist: py-algorand-sdk (==1.13.1)
Requires-Dist: pyteal (==0.10.0)
Project-URL: Repository, https://github.com/AlgoWorldNFT/algoworld-contracts
